Metadata-Version: 1.1
Name: anouman
Version: 0.0.5.0
Summary: Rapidly deploy your django project behind gunicorn and nginx
Home-page: https://github.com/gnulnx/anouman
Author: John Furr
Author-email: anouman.dev@gmail.com
License: BSD
Download-URL: https://github.com/gnulnx/anouman/tree/0.0.5.0
Platform: UNKNOWN
Classifier: Environment :: Web Environment
Classifier: Development Status :: 2 - Pre-Alpha
Classifier: Intended Audience :: Developers
Classifier: Programming Language :: Python
Classifier: Topic :: Internet :: WWW/HTTP
Classifier: Topic :: Internet :: WWW/HTTP :: WSGI
